h5py-3.15.0.dist-info/RECORD
h5py-3.15.0.dist-info/WHEEL
h5py-3.15.0.dist-info/top_level.txt
h5py-3.15.0.dist-info/METADATA
h5py-3.15.0.dist-info/licenses/LICENSE
h5py-3.15.0.dist-info/licenses/licenses/pytables.txt
h5py-3.15.0.dist-info/licenses/licenses/python.txt
h5py-3.15.0.dist-info/licenses/licenses/license.txt
h5py-3.15.0.dist-info/licenses/licenses/hdf5.txt
h5py-3.15.0.dist-info/licenses/licenses/stdint.txt
h5py-3.15.0.dist-info/licenses/lzf/LICENSE.txt
h5py/h5d.cpython-314-darwin.so
h5py/_npystrings.cpython-314-darwin.so
h5py/h5py_warnings.py
h5py/h5ds.cpython-314-darwin.so
h5py/h5l.cpython-314-darwin.so
h5py/version.py
h5py/h5f.cpython-314-darwin.so
h5py/h5fd.cpython-314-darwin.so
h5py/defs.cpython-314-darwin.so
h5py/_proxy.cpython-314-darwin.so
h5py/__init__.py
h5py/h5s.cpython-314-darwin.so
h5py/utils.cpython-314-darwin.so
h5py/_conv.cpython-314-darwin.so
h5py/h5t.cpython-314-darwin.so
h5py/h5.cpython-314-darwin.so
h5py/h5o.cpython-314-darwin.so
h5py/_errors.cpython-314-darwin.so
h5py/_objects.cpython-314-darwin.so
h5py/h5g.cpython-314-darwin.so
h5py/h5a.cpython-314-darwin.so
h5py/h5pl.cpython-314-darwin.so
h5py/h5p.cpython-314-darwin.so
h5py/h5i.cpython-314-darwin.so
h5py/h5ac.cpython-314-darwin.so
h5py/ipy_completer.py
h5py/_selector.cpython-314-darwin.so
h5py/h5r.cpython-314-darwin.so
h5py/h5z.cpython-314-darwin.so
h5py/tests/test_dimension_scales.py
h5py/tests/test_attribute_create.py
h5py/tests/test_file_image.py
h5py/tests/conftest.py
h5py/tests/test_h5d_direct_chunk.py
h5py/tests/test_h5f.py
h5py/tests/test_dataset_getitem.py
h5py/tests/test_h5z.py
h5py/tests/test_group.py
h5py/tests/test_errors.py
h5py/tests/test_dataset_swmr.py
h5py/tests/test_slicing.py
h5py/tests/test_h5pl.py
h5py/tests/test_attrs.py
h5py/tests/__init__.py
h5py/tests/test_attrs_data.py
h5py/tests/test_h5t.py
h5py/tests/test_big_endian_file.py
h5py/tests/test_h5p.py
h5py/tests/test_dims_dimensionproxy.py
h5py/tests/test_h5o.py
h5py/tests/test_datatype.py
h5py/tests/common.py
h5py/tests/test_h5s.py
h5py/tests/test_dataset.py
h5py/tests/test_file.py
h5py/tests/test_selections.py
h5py/tests/test_ros3.py
h5py/tests/test_dtype.py
h5py/tests/test_h5.py
h5py/tests/test_file2.py
h5py/tests/test_completions.py
h5py/tests/test_filters.py
h5py/tests/test_base.py
h5py/tests/test_objects.py
h5py/tests/test_npystrings.py
h5py/tests/test_file_alignment.py
