Metadata-Version: 2.4
Name: h5py
Version: 3.15.0
Summary: Read and write HDF5 files from Python
Author-email: Andrew Collette <andrew.collette@gmail.com>
Maintainer-email: Thomas Kluyver <thomas@kluyver.me.uk>, Thomas A Caswell <tcaswell@bnl.gov>
License-Expression: BSD-3-Clause
Project-URL: Homepage, https://www.h5py.org/
Project-URL: Source, https://github.com/h5py/h5py
Project-URL: Documentation, https://docs.h5py.org/en/stable/
Project-URL: Release notes, https://docs.h5py.org/en/stable/whatsnew/index.html
Project-URL: Discussion forum, https://forum.hdfgroup.org/c/hdf5/h5py
Classifier: Development Status :: 5 - Production/Stable
Classifier: Intended Audience :: Developers
Classifier: Intended Audience :: Information Technology
Classifier: Intended Audience :: Science/Research
Classifier: Operating System :: Unix
Classifier: Operating System :: POSIX :: Linux
Classifier: Operating System :: MacOS :: MacOS X
Classifier: Operating System :: Microsoft :: Windows
Classifier: Programming Language :: Cython
Classifier: Programming Language :: Python
Classifier: Programming Language :: Python :: 3
Classifier: Programming Language :: Python :: 3.10
Classifier: Programming Language :: Python :: 3.11
Classifier: Programming Language :: Python :: 3.12
Classifier: Programming Language :: Python :: 3.13
Classifier: Programming Language :: Python :: 3.14
Classifier: Programming Language :: Python :: Free Threading :: 1 - Unstable
Classifier: Programming Language :: Python :: Implementation :: CPython
Classifier: Topic :: Scientific/Engineering
Classifier: Topic :: Database
Classifier: Topic :: Software Development :: Libraries :: Python Modules
Requires-Python: >=3.10
License-File: LICENSE
License-File: lzf/LICENSE.txt
License-File: licenses/hdf5.txt
License-File: licenses/license.txt
License-File: licenses/pytables.txt
License-File: licenses/python.txt
License-File: licenses/stdint.txt
Requires-Dist: numpy>=1.21.2
Dynamic: license-file
Dynamic: requires-dist
